lvdb/__init__.py
lvdb/db_cache.py
lvdb/error_handler.py
lvdb/lvinstance.py
lvdb/lvshard.py
lvdb/profiler.py
lvdb/shard_math.py
lvdb/timer.py
lvdb/interfaces/__init__.py
lvdb/interfaces/instance_interface.py
lvdb/interfaces/shard_interface.py
lvdb-2.1.2.dist-info/METADATA
lvdb-2.1.2.dist-info/WHEEL
lvdb-2.1.2.dist-info/licenses/LICENSE
lvdb-2.1.2.dist-info/RECORD
