Metadata-Version: 2.1
Name: lvdb
Version: 2.1.2
Summary: A package to locally shard vector data to conserve memory in memory-limited environments
Author-email: TripIe <t9379115@gmail.com>
License-File: LICENSE
Classifier: License :: OSI Approved :: MIT License
Classifier: Operating System :: OS Independent
Classifier: Programming Language :: Python :: 3
Requires-Python: >=3.10
